score.sass-0.0.4-py3.4-nspkg.pth
score/sass/__init__.py
score/sass/_init.py
score/sass/renderer.py
score.sass-0.0.4.dist-info/DESCRIPTION.rst
score.sass-0.0.4.dist-info/METADATA
score.sass-0.0.4.dist-info/RECORD
score.sass-0.0.4.dist-info/WHEEL
score.sass-0.0.4.dist-info/metadata.json
score.sass-0.0.4.dist-info/namespace_packages.txt
score.sass-0.0.4.dist-info/top_level.txt
